euro_2024_poster_generator/__init__.py
euro_2024_poster_generator/image_generator.py
euro_2024_poster_generator-3.0.1.dist-info/METADATA
euro_2024_poster_generator-3.0.1.dist-info/WHEEL
euro_2024_poster_generator-3.0.1.dist-info/top_level.txt
euro_2024_poster_generator-3.0.1.dist-info/RECORD
