Metadata-Version: 2.1
Name: euro_2024_poster_generator
Version: 3.0.1
Summary: A Python package to generate Euro 2024 match poster with Pillow
Home-page: https://github.com/Kajaia/euro-2024-poster-generator
Author: Lasha Kajaia
Author-email: lasha@kajaia.dev
Classifier: Programming Language :: Python :: 3
Classifier: Operating System :: OS Independent
Requires-Python: >=3.12
Requires-Dist: pillow
Requires-Dist: requests
Requires-Dist: python-slugify
